clima_anom/__init__.py
clima_anom/geometries/__init__.py
clima_anom/geometries/geo.py
clima_anom/others/__init__.py
clima_anom/others/mixture.py
clima_anom/processing/__init__.py
clima_anom/processing/preprocess.py
clima_anom/reading/__init__.py
clima_anom/reading/prenetcdf.py
clima_anom/statistic/__init__.py
clima_anom/statistic/metrics.py
clima_anom-0.7.6.dist-info/METADATA
clima_anom-0.7.6.dist-info/WHEEL
clima_anom-0.7.6.dist-info/top_level.txt
clima_anom-0.7.6.dist-info/RECORD
