Metadata-Version: 2.1
Name: clima-anom
Version: 0.7.6
Summary: Obtain the climatology and anomalies only for monthly data.
Home-page: https://github.com/mhacarthur/clima-anom
Author: Cesar Arturo Sanchez Pena
Author-email: arturo66cta@gmail.com
License: MIT
Keywords: climatology,anomalies,monthly,correlation,netcdf,MAE,RMSE,BIAS,Create netcdf,remove continent,remove ocean,shapefile remove
Platform: UNKNOWN
Requires-Python: >=3.5
Requires-Dist: numpy (==1.21.2)
Requires-Dist: pandas (==1.3.4)
